drought_indices_python/Lmoments.py
drought_indices_python/__init__.py
drought_indices_python/indices.py
drought_indices_python/metrics.py
drought_indices_python-0.1.4.dist-info/licenses/LICENSE
drought_indices_python-0.1.4.dist-info/METADATA
drought_indices_python-0.1.4.dist-info/WHEEL
drought_indices_python-0.1.4.dist-info/top_level.txt
drought_indices_python-0.1.4.dist-info/RECORD
