Metadata-Version: 2.4
Name: drought_indices_python
Version: 0.1.4
Summary: A Python package for calculating and analyzing drought indices.
Home-page: https://github.com/ktripa/drought_indices_python
Author: Kumar Puran Tripathy
Author-email: tripathypuranbdk@gmail.com
Classifier: Programming Language :: Python :: 3
Classifier: License :: OSI Approved :: MIT License
Classifier: Operating System :: OS Independent
Classifier: Topic :: Scientific/Engineering :: Atmospheric Science
Classifier: Topic :: Scientific/Engineering :: Hydrology
Classifier: Development Status :: 3 - Alpha
Requires-Python: >=3.7
License-File: LICENSE
Dynamic: author
Dynamic: author-email
Dynamic: classifier
Dynamic: description
Dynamic: description-content-type
Dynamic: home-page
Dynamic: license-file
Dynamic: requires-python
Dynamic: summary
